<?xml version="1.0" encoding="UTF-8"?>
<!DOCTYPE mapper PUBLIC "-//mybatis.org//DTD Mapper 3.0//EN" "http://mybatis.org/dtd/mybatis-3-mapper.dtd">

<mapper namespace="com.sqqmall.modules.customer.dao.CustomerDao">

    <!-- 可根据自己的需求，是否要使用 -->
    <resultMap type="com.sqqmall.modules.customer.entity.CustomerEntity" id="customerMap">
        <result property="id" column="id"/>
        <result property="mobile" column="mobile"/>
        <result property="password" column="password"/>
        <result property="salt" column="salt"/>
        <result property="realName" column="real_name"/>
        <result property="nickName" column="nick_name"/>
        <result property="sex" column="sex"/>
        <result property="birthday" column="birthday"/>
        <result property="province" column="province"/>
        <result property="city" column="city"/>
        <result property="area" column="area"/>
        <result property="address" column="address"/>
        <result property="createTime" column="create_time"/>
        <result property="updateTime" column="update_time"/>
        <result property="createId" column="create_id"/>
        <result property="updateId" column="update_id"/>
        <result property="remarks" column="remarks"/>
        <result property="version" column="version"/>
        <result property="enable" column="enable"/>
        <result property="source" column="source"/>
    </resultMap>


</mapper>
